MANIFEST.in
README.rst
setup.py
docs/COPYRIGHT.txt
docs/HISTORY.rst
docs/LICENSE.txt
src/http_session/__init__.py
src/http_session/cookie.py
src/http_session/meta.py
src/http_session/session.py
src/http_session.egg-info/PKG-INFO
src/http_session.egg-info/SOURCES.txt
src/http_session.egg-info/dependency_links.txt
src/http_session.egg-info/not-zip-safe
src/http_session.egg-info/requires.txt
src/http_session.egg-info/top_level.txt
tests/conftest.py
tests/test_cookies.py
tests/test_session.py
tests/test_store.py
tests/test_wsgi_middleware.py