Metadata-Version: 2.1
Name: http-session
Version: 0.1
Summary: Server-side session components.
Home-page: https://github.com/HorsemanWSGI/http_session
Author: Souheil Chelfouh
Author-email: trollfot@gmail.com
License: UNKNOWN
Keywords: HTTP,Session
Platform: UNKNOWN
Classifier: License :: OSI Approved :: BSD License
Classifier: Programming Language :: Python :: 3.10
Classifier: Programming Language :: Python :: 3.8
Classifier: Programming Language :: Python :: 3.9
Classifier: Topic :: Internet :: WWW/HTTP :: WSGI
Provides-Extra: test
